{
  "Title": "CCB4",
  "Author": "AdamD.",
  "Events": [
    {"Time": 0},
    {"Time": 1,"Action":"Shoot"}, 
    {"Time": 1,"Action": "RandomWalk"},
    {"Time": 2,"Action":"Shoot"}, 
    {"Time": 2,"Action": "RandomWalk"},
    {"Time": 3,"Action":"Shoot"}, 
    {"Time": 3,"Action": "RandomWalk"},
    {"Time": 4, "Action":"SetSpeed", "Amt":4.67},
    {"Time": 4, "Action":"SetToPlayerY"},
    {"Time": 4, "Action":"SetX", "Amt":-7},
    {"Time": 4, "Action":"MoveToX", "Amt":7},
    {"Time": 4,"Anim": "SpinShoot","Amt":3},

    {"Time": 9,"Action":"Shoot"},
    {"Time": 9,"Action": "RandomWalk"},
    {"Time": 10,"Action":"Shoot"},
    {"Time": 10,"Action": "RandomWalk"},
    {"Time": 11,"Action":"Shoot"},
    {"Time": 11,"Action": "RandomWalk"},
    {"Time": 13, "Action":"SetSpeed", "Amt":4.67},
    {"Time": 13, "Action":"SetToPlayerY"},
    {"Time": 13, "Action":"SetX", "Amt":-7},
    {"Time": 13, "Action":"MoveToX", "Amt":7},
    {"Time": 13,"Anim": "SpinShoot","Amt":3},

    {"Time": 17,"Dialogue":"Talk to myself,"},
    {"Time": 17,"Action":"SetX", "Amt":7},
    {"Time": 17,"Action":"SetY", "Amt":0},
    {"Time": 17.5, "Action":"ShootAtPlayer"},
    {"Time": 18, "Action":"ShootAtPlayer"},
 
    {"Time": 20,"Dialogue":"Cuz no one else,"},
    {"Time": 20,"Action":"SetX", "Amt":-7},
    {"Time": 20,"Action":"SetY", "Amt":0},
    {"Time": 20.5, "Action":"ShootAtPlayer"},
    {"Time": 21, "Action":"ShootAtPlayer"},

    {"Time": 22,"Dialogue":"Knows the way I do when I feel overwhelmed"},
    {"Time": 22,"Action":"SetX", "Amt":0},
    {"Time": 22,"Action":"SetY", "Amt":0},
    {"Time": 23, "Action":"ShootAtPlayer"},
    {"Time": 24, "Action":"ShootAtPlayer"},
    {"Time": 25, "Action":"ShootAtPlayer"},
    {"Time": 25.5, "Action":"ShootAtPlayer"},
    {"Time": 26, "Action":"ShootAtPlayer"},

    {"Time": 27,"Dialogue":"Made the wrong turn,"},
    {"Time": 27,"Action":"SetX", "Amt":7},
    {"Time": 27,"Action":"SetY", "Amt":0},
    {"Time": 27.5, "Action":"ShootAtPlayer"},
    {"Time": 28, "Action":"ShootAtPlayer"},
 
    {"Time": 29,"Dialogue":"And I got burned"},
    {"Time": 29,"Action":"SetX", "Amt":-7},
    {"Time": 29,"Action":"SetY", "Amt":0},
    {"Time": 29.5, "Action":"ShootAtPlayer"},
    {"Time": 30, "Action":"ShootAtPlayer"},

    {"Time": 32,"Dialogue":"Every decision weighing on me in my world,"},
    {"Time": 32,"Action":"SetX", "Amt":0},
    {"Time": 32,"Action":"SetY", "Amt":0},
    {"Time": 32, "Action":"ShootAtPlayer"},
    {"Time": 33, "Action":"ShootAtPlayer"},
    {"Time": 34, "Action":"ShootAtPlayer"},
    {"Time": 35, "Action":"ShootAtPlayer"},
    {"Time": 35.5, "Action":"ShootAtPlayer"},
    {"Time": 36, "Action":"ShootAtPlayer"},

    {"Time": 36,"Dialogue":"So I just try to breath,"},
    {"Time": 36,"Action":"SetX", "Amt":-7},
    {"Time": 36,"Action":"SetY", "Amt":4},
    {"Time": 36,"Action":"SetSpeed", "Amt":4},
    {"Time": 36,"Action":"MoveToY", "Amt":-4},
    {"Time": 37, "Action":"ShootAtPlayer"},
    {"Time": 38, "Action":"ShootAtPlayer"},

    {"Time": 38,"Dialogue":"And I'll try to see,"},
    {"Time": 38,"Action":"SetX", "Amt":0},
    {"Time": 38,"Action":"SetY", "Amt":4},
    {"Time": 38,"Action":"MoveToY", "Amt":-4},
    {"Time": 39, "Action":"ShootAtPlayer"},
    {"Time": 40, "Action":"ShootAtPlayer"},

    {"Time": 40,"Dialogue":"all of the reasons we,"},
    {"Time": 40,"Action":"SetX", "Amt":7},
    {"Time": 40,"Action":"SetY", "Amt":4},
    {"Time": 40,"Action":"MoveToY", "Amt":-4},
    {"Time": 41, "Action":"ShootAtPlayer"},
    {"Time": 42, "Action":"ShootAtPlayer"},

    {"Time": 42,"Dialogue":"are where we're meant to be."},
    {"Time": 42,"Action":"SetX", "Amt":-7},
    {"Time": 42,"Action":"SetY", "Amt":4},
    {"Time": 42,"Action":"MoveToY", "Amt":-4},
    {"Time": 43, "Action":"ShootAtPlayer"},
    {"Time": 44, "Action":"ShootAtPlayer"},

    {"Time": 44,"Dialogue":"I know I lost the race,"},
    {"Time": 44,"Action":"SetX", "Amt":7},
    {"Time": 44,"Action":"SetY", "Amt":4},
    {"Time": 44,"Action":"MoveToY", "Amt":-4},
    {"Time": 45, "Action":"ShootAtPlayer"},
    {"Time": 46, "Action":"ShootAtPlayer"},

    {"Time": 46,"Dialogue":"Backfired in my face,"},
    {"Time": 46,"Action":"SetX", "Amt":0},
    {"Time": 46,"Action":"SetY", "Amt":4},
    {"Time": 46,"Action":"MoveToY", "Amt":-4},
    {"Time": 47, "Action":"ShootAtPlayer"},
    {"Time": 48, "Action":"ShootAtPlayer"},

    {"Time": 48,"Dialogue":"But I'll find my way,"},
    {"Time": 48,"Action":"SetX", "Amt":0},
    {"Time": 48,"Action":"SetY", "Amt":4},
    {"Time": 48,"Action":"MoveToY", "Amt":-4},
    {"Time": 49, "Action":"ShootAtPlayer"},
    {"Time": 50, "Action":"ShootAtPlayer"},

    {"Time": 51,"Dialogue":"Eventually."},
    {"Time": 51, "Action":"ShootAtPlayer"},
    {"Time": 51.5, "Action":"ShootAtPlayer"},
    {"Time": 52, "Action":"ShootAtPlayer"},

    {"Time": 54,"Dialogue":"Oo-oh!"},
    {"Time": 54, "Action":"SetSpeed", "Amt":7},
    {"Time": 54, "Action":"SetToPlayerY"},
    {"Time": 54, "Action":"SetX", "Amt":-7},
    {"Time": 54, "Action":"MoveToX", "Amt":7},
    {"Time": 54, "Action":"ShootAtPlayer"},
    {"Time": 54.5, "Action":"ShootAtPlayer"},
    {"Time": 55, "Action":"ShootAtPlayer"},

    {"Time": 56,"Dialogue":"The regret in my head got me taken over!"},
    {"Time": 56,"Action":"SetX", "Amt":0},
    {"Time": 56,"Action":"SetY", "Amt":0},
    {"Time": 56,"Anim": "SpinShoot","Amt":2},
    {"Time": 56, "Action":"ShootAtPlayer"},
    {"Time": 56.5, "Action":"ShootAtPlayer"},
    {"Time": 57, "Action":"ShootAtPlayer"},
    {"Time": 58, "Action":"ShootAtPlayer"},

    {"Time": 59,"Dialogue":"Oo-oh!"},
    {"Time": 59, "Action":"SetSpeed", "Amt":7},
    {"Time": 59, "Action":"SetToPlayerY"},
    {"Time": 59, "Action":"SetX", "Amt":-7},
    {"Time": 59, "Action":"MoveToX", "Amt":7},
    {"Time": 59, "Action":"ShootAtPlayer"},
    {"Time": 59.5, "Action":"ShootAtPlayer"},
    {"Time": 60, "Action":"ShootAtPlayer"},

    {"Time": 61,"Dialogue":"I'm alive and suprised, and it makes me wonder"},
    {"Time": 61,"Action":"SetX", "Amt":0},
    {"Time": 61,"Action":"SetY", "Amt":0},
    {"Time": 61,"Anim": "SpinShoot","Amt":2},
    {"Time": 61, "Action":"ShootAtPlayer"},
    {"Time": 61.5, "Action":"ShootAtPlayer"},
    {"Time": 62, "Action":"ShootAtPlayer"},
    {"Time": 63, "Action":"ShootAtPlayer"},

    {"Time": 64,"Dialogue":"Oo-oh!"},
    {"Time": 64, "Action":"SetSpeed", "Amt":7},
    {"Time": 64, "Action":"SetToPlayerY"},
    {"Time": 64, "Action":"SetX", "Amt":-7},
    {"Time": 64, "Action":"MoveToX", "Amt":7},
    {"Time": 64, "Action":"ShootAtPlayer"},
    {"Time": 64.5, "Action":"ShootAtPlayer"},
    {"Time": 65, "Action":"ShootAtPlayer"},

    {"Time": 66,"Dialogue":"If they say 'everything that you learned this life"},
    {"Time": 66,"Action":"SetX", "Amt":0},
    {"Time": 66,"Action":"SetY", "Amt":0},
    {"Time": 66, "Action":"ShootAtPlayer"},
    {"Time": 66.5, "Action":"ShootAtPlayer"},
    {"Time": 67, "Action":"ShootAtPlayer"},

    {"Time": 68,"Dialogue":"makes you wise',"},
    {"Time": 68,"Action":"SetX", "Amt":-7},
    {"Time": 68,"Action":"SetY", "Amt":0},
    {"Time": 68, "Action":"ShootAtPlayer"},
    {"Time": 68.33,"Action":"SetX", "Amt":0},
    {"Time": 68.33,"Action":"SetY", "Amt":4},
    {"Time": 68.33, "Action":"ShootAtPlayer"},
    {"Time": 68.66,"Action":"SetX", "Amt":7},
    {"Time": 68.66, "Action":"SetY", "Amt":0},
    {"Time": 68.66, "Action":"ShootAtPlayer"},

    {"Time": 70,"Dialogue":"I'm doing it, doing it right!"},
    {"Time": 70,"Action":"SetX", "Amt":0},
    {"Time": 70,"Action":"SetY", "Amt":0},
    {"Time": 70,"Anim": "SpinShoot","Amt":2},
    {"Time": 70.5, "Action":"ShootAtPlayer"},
    {"Time": 71, "Action":"ShootAtPlayer"},
    {"Time": 71.5, "Action":"ShootAtPlayer"},

    {"Time": 73,"Dialogue":"Made enemies"},
    {"Time": 73,"Action":"SetX", "Amt":7},
    {"Time": 73,"Action":"SetY", "Amt":0},
    {"Time": 73.5,"Action":"ShootAtPlayer"},
    {"Time": 74,"Action":"ShootAtPlayer"},
 
    {"Time": 75,"Dialogue":"They don't scare me,"},
    {"Time": 75,"Action":"SetX", "Amt":-7},
    {"Time": 75,"Action":"SetY", "Amt":0},
    {"Time": 75.5,"Action":"ShootAtPlayer"},
    {"Time": 76,"Action":"ShootAtPlayer"},

    {"Time": 77,"Dialogue":"Cuz I got everyone I need her on my team"},
    {"Time": 77,"Action":"SetX", "Amt":0},
    {"Time": 77,"Action":"SetY", "Amt":0},
    {"Time": 78,"Action":"ShootAtPlayer"},
    {"Time": 79,"Action":"ShootAtPlayer"},
    {"Time": 80,"Action":"ShootAtPlayer"},
    {"Time": 80.5,"Action":"ShootAtPlayer"},
    {"Time": 81,"Action":"ShootAtPlayer"},

    {"Time": 82,"Dialogue":"And we will fight"},
    {"Time": 82,"Action":"SetX", "Amt":7},
    {"Time": 82,"Action":"SetY", "Amt":0},
    {"Time": 82.5, "Action":"ShootAtPlayer"},
    {"Time": 83, "Action":"ShootAtPlayer"},
 
    {"Time": 84,"Dialogue":"We're meant to thrive"},
    {"Time": 84,"Action":"SetX", "Amt":-7},
    {"Time": 84,"Action":"SetY", "Amt":0},
    {"Time": 84.5, "Action":"ShootAtPlayer"},
    {"Time": 85, "Action":"ShootAtPlayer"},

    {"Time": 86,"Dialogue":"in any circumstance you throw us in tonight"},
    {"Time": 86,"Action":"SetX", "Amt":0},
    {"Time": 86,"Action":"SetY", "Amt":0},
    {"Time": 86, "Action":"ShootAtPlayer"},
    {"Time": 87, "Action":"ShootAtPlayer"},
    {"Time": 88, "Action":"ShootAtPlayer"},
    {"Time": 89, "Action":"ShootAtPlayer"},
    {"Time": 89.5, "Action":"ShootAtPlayer"},
    {"Time": 90, "Action":"ShootAtPlayer"},

    {"Time": 92, "Dialogue":"Inside of my mind I've been searchin"},
    {"Time": 92, "Action": "RandomWalk"},
    {"Time": 92, "Action":"ShootAtPlayer"},
    {"Time": 93, "Action":"ShootAtPlayer"},
    {"Time": 94, "Action":"ShootAtPlayer"},

    {"Time": 94, "Dialogue":"For the words that'll cure all my hurtin"},
    {"Time": 94, "Action": "RandomWalk"},
    {"Time": 94, "Action":"ShootAtPlayer"},
    {"Time": 95, "Action":"ShootAtPlayer"},
    {"Time": 96, "Action":"ShootAtPlayer"},
    
    {"Time": 97, "Dialogue":"Tough love got me feelin deservin"},
    {"Time": 97,"Action":"SetX", "Amt":0},
    {"Time": 97,"Action":"SetY", "Amt":4},
    {"Time": 97, "Action":"ShootAtPlayer"},
    {"Time": 97.5,"Action":"Shoot"},
    {"Time": 98, "Action":"ShootAtPlayer"},
    {"Time": 98.5,"Action":"Shoot"},


    {"Time": 99, "Dialogue":"Rip back the curtain, that's how I'm learnin"},
    {"Time": 99, "Who":"Obstacle","Action":"SetX", "Amt":-7},
    {"Time": 101, "Who":"Obstacle","Action":"SetY", "Amt":2.25},

    {"Time": 101, "Dialogue":"Reflect on the mess I created"},

    {"Time": 103, "Dialogue":"Respect for the test I hated"},

    {"Time": 105, "Dialogue":"Making all the winning decisions"},

    {"Time": 107, "Dialogue":"With high precision"},

    {"Time": 108, "Dialogue":"not that I'd listen"},

    {"Time": 110,"Dialogue":"Oo-oh!"},
    {"Time": 110, "Action":"SetSpeed", "Amt":7},
    {"Time": 110, "Action":"SetToPlayerY"},
    {"Time": 110, "Action":"SetX", "Amt":7},
    {"Time": 110, "Action":"MoveToX", "Amt":-7},
    {"Time": 110, "Action":"ShootAtPlayer"},
    {"Time": 110.5, "Action":"ShootAtPlayer"},
    {"Time": 111, "Action":"ShootAtPlayer"},

    {"Time": 112,"Dialogue":"The regret in my head got me taken over!"},
    {"Time": 112,"Action":"SetX", "Amt":0},
    {"Time": 112,"Action":"SetY", "Amt":0},
    {"Time": 112,"Anim": "SpinShoot","Amt":2},
    {"Time": 112, "Action":"ShootAtPlayer"},
    {"Time": 112.5, "Action":"ShootAtPlayer"},
    {"Time": 112, "Action":"ShootAtPlayer"},
    {"Time": 113, "Action":"ShootAtPlayer"},

    {"Time": 114,"Dialogue":"Oo-oh!"},
    {"Time": 114, "Action":"SetSpeed", "Amt":7},
    {"Time": 114, "Action":"SetToPlayerY"},
    {"Time": 114, "Action":"SetX", "Amt":7},
    {"Time": 114, "Action":"MoveToX", "Amt":-7},
    {"Time": 114, "Action":"ShootAtPlayer"},
    {"Time": 114.5, "Action":"ShootAtPlayer"},
    {"Time": 115, "Action":"ShootAtPlayer"},

    {"Time": 116,"Dialogue":"I'm alive and suprised, and it makes me wonder"},
    {"Time": 116,"Action":"SetX", "Amt":0},
    {"Time": 116,"Action":"SetY", "Amt":0},
    {"Time": 116,"Anim": "SpinShoot","Amt":2},
    {"Time": 116, "Action":"ShootAtPlayer"},
    {"Time": 116.5, "Action":"ShootAtPlayer"},
    {"Time": 117, "Action":"ShootAtPlayer"},
    {"Time": 118, "Action":"ShootAtPlayer"},

    {"Time": 118,"Dialogue":"Oo-oh!"},
    {"Time": 118, "Action":"SetSpeed", "Amt":7},
    {"Time": 118, "Action":"SetToPlayerY"},
    {"Time": 118, "Action":"SetX", "Amt":7},
    {"Time": 118, "Action":"MoveToX", "Amt":-7},
    {"Time": 118, "Action":"ShootAtPlayer"},
    {"Time": 118.5, "Action":"ShootAtPlayer"},
    {"Time": 119, "Action":"ShootAtPlayer"},

    {"Time": 120,"Dialogue":"If they say 'everything that you learned this life"},
    {"Time": 120,"Action":"SetX", "Amt":0},
    {"Time": 120,"Action":"SetY", "Amt":0},
    {"Time": 120, "Action":"ShootAtPlayer"},
    {"Time": 120.5, "Action":"ShootAtPlayer"},
    {"Time": 121, "Action":"ShootAtPlayer"},

    {"Time": 122,"Dialogue":"makes you wise',"},
    {"Time": 122,"Action":"SetX", "Amt":-7},
    {"Time": 122,"Action":"SetY", "Amt":0},
    {"Time": 122, "Action":"ShootAtPlayer"},
    {"Time": 122.33,"Action":"SetX", "Amt":0},
    {"Time": 122.33,"Action":"SetY", "Amt":-4},
    {"Time": 122.33, "Action":"ShootAtPlayer"},
    {"Time": 122.66,"Action":"SetX", "Amt":7},
    {"Time": 122.66, "Action":"SetY", "Amt":0},
    {"Time": 122.66, "Action":"ShootAtPlayer"},

    {"Time": 123,"Dialogue":"I'm doing it, doing it right!"},
    {"Time": 123,"Action":"SetX", "Amt":0},
    {"Time": 123,"Action":"SetY", "Amt":0},
    {"Time": 123,"Anim": "SpinShoot","Amt":2},
    {"Time": 123.5, "Action":"ShootAtPlayer"},
    {"Time": 124, "Action":"ShootAtPlayer"},
    {"Time": 124.5, "Action":"ShootAtPlayer"},

    {"Time": 126, "Dialogue":"Made the best out the stress I've been holdin"},
    {"Time": 130, "Dialogue":"I'm the one, only one- I've been chosen"},
    {"Time": 134, "Dialogue":"Tell the sorrow there's always tomorrow, always tomorrow, for another go"},





    {"Time": 209}
  ]
}